[
  {
    "entry_id": "knowledge-capitalization-e63cf241b6",
    "timestamp": "2026-07-07T07:23:12Z",
    "release": "FOUNDATION-0010",
    "status": "CAPITALIZED",
    "event_type": "knowledge_capitalization",
    "summary": "Knowledge PK-001 capitalized into knowledge/professional_knowledge.json.",
    "package_id": "KCAP-20260707T072312Z-b0201d",
    "knowledge_id": "PK-001",
    "knowledge_type": "professional"
  },
  {
    "entry_id": "knowledge-capitalization-a927816298",
    "timestamp": "2026-07-07T07:23:22Z",
    "release": "FOUNDATION-0010",
    "status": "CAPITALIZED",
    "event_type": "knowledge_capitalization",
    "summary": "Knowledge PK-001 capitalized into knowledge/professional_knowledge.json.",
    "package_id": "KCAP-20260707T072322Z-48a607",
    "knowledge_id": "PK-001",
    "knowledge_type": "professional"
  },
  {
    "entry_id": "knowledge-capitalization-5b8def756d",
    "timestamp": "2026-07-07T07:23:54Z",
    "release": "FOUNDATION-0010",
    "status": "CAPITALIZED",
    "event_type": "knowledge_capitalization",
    "summary": "Knowledge PK-001 capitalized into knowledge/professional_knowledge.json.",
    "package_id": "KCAP-20260707T072354Z-d3f015",
    "knowledge_id": "PK-001",
    "knowledge_type": "professional"
  },
  {
    "entry_id": "knowledge-capitalization-7ec498aa21",
    "timestamp": "2026-07-07T08:08:30Z",
    "release": "FOUNDATION-0012",
    "status": "CAPITALIZED",
    "event_type": "knowledge_capitalization",
    "summary": "Knowledge PK-001 capitalized into knowledge/professional_knowledge.json.",
    "package_id": "KCAP-20260707T080830Z-3c8e3f",
    "knowledge_id": "PK-001",
    "knowledge_type": "professional"
  },
  {
    "entry_id": "knowledge-capitalization-149fa2d845",
    "timestamp": "2026-07-07T11:17:15Z",
    "release": "FOUNDATION-0013",
    "status": "CAPITALIZED",
    "event_type": "knowledge_capitalization",
    "summary": "Knowledge BK-001 capitalized into business_domains/bon_buasson/business_knowledge.json.",
    "package_id": "KCAP-20260707T111715Z-eeca29",
    "knowledge_id": "BK-001",
    "knowledge_type": "business",
    "domain": "bon_buasson"
  },
  {
    "entry_id": "knowledge-capitalization-87a5337c4b",
    "timestamp": "2026-07-07T11:18:32Z",
    "release": "FOUNDATION-0013",
    "status": "CAPITALIZED",
    "event_type": "knowledge_capitalization",
    "summary": "Knowledge BK-001 capitalized into business_domains/bon_buasson/business_knowledge.json.",
    "package_id": "KCAP-20260707T111832Z-2bb5d6",
    "knowledge_id": "BK-001",
    "knowledge_type": "business",
    "domain": "bon_buasson"
  },
  {
    "entry_id": "knowledge-capitalization-4bb57134e0",
    "timestamp": "2026-07-07T18:39:15Z",
    "release": "LABORATORY-KNOWLEDGE-0005",
    "status": "CAPITALIZED",
    "event_type": "knowledge_capitalization",
    "summary": "Knowledge PK-005 capitalized into knowledge/professional_knowledge.json.",
    "package_id": "KCAP-20260707T183915Z-b9c80e",
    "knowledge_id": "PK-005",
    "knowledge_type": "professional",
    "domain": null
  },
  {
    "entry_id": "knowledge-capitalization-341ec7e115",
    "timestamp": "2026-07-07T18:39:15Z",
    "release": "LABORATORY-KNOWLEDGE-0005",
    "status": "CAPITALIZED",
    "event_type": "knowledge_capitalization",
    "summary": "Knowledge BK-005 capitalized into business_domains/bon_buasson/business_knowledge.json.",
    "package_id": "KCAP-20260707T183915Z-878eda",
    "knowledge_id": "BK-005",
    "knowledge_type": "business",
    "domain": "bon_buasson"
  },
  {
    "entry_id": "knowledge-capitalization-705485b275",
    "timestamp": "2026-07-07T18:40:16Z",
    "release": "LABORATORY-KNOWLEDGE-0005",
    "status": "CAPITALIZED",
    "event_type": "knowledge_capitalization",
    "summary": "Knowledge PK-006 capitalized into knowledge/professional_knowledge.json.",
    "package_id": "KCAP-20260707T184016Z-c80da4",
    "knowledge_id": "PK-006",
    "knowledge_type": "professional",
    "domain": null
  },
  {
    "entry_id": "knowledge-capitalization-12b7f9c63f",
    "timestamp": "2026-07-07T18:40:16Z",
    "release": "LABORATORY-KNOWLEDGE-0005",
    "status": "CAPITALIZED",
    "event_type": "knowledge_capitalization",
    "summary": "Knowledge BK-006 capitalized into business_domains/bon_buasson/business_knowledge.json.",
    "package_id": "KCAP-20260707T184016Z-344fc2",
    "knowledge_id": "BK-006",
    "knowledge_type": "business",
    "domain": "bon_buasson"
  },
  {
    "entry_id": "knowledge-capitalization-8fec5d3802",
    "timestamp": "2026-07-07T18:40:43Z",
    "release": "LABORATORY-KNOWLEDGE-0005",
    "status": "CAPITALIZED",
    "event_type": "knowledge_capitalization",
    "summary": "Knowledge PK-007 capitalized into knowledge/professional_knowledge.json.",
    "package_id": "KCAP-20260707T184042Z-43dfe7",
    "knowledge_id": "PK-007",
    "knowledge_type": "professional",
    "domain": null
  },
  {
    "entry_id": "knowledge-capitalization-dcbea72add",
    "timestamp": "2026-07-07T18:40:43Z",
    "release": "LABORATORY-KNOWLEDGE-0005",
    "status": "CAPITALIZED",
    "event_type": "knowledge_capitalization",
    "summary": "Knowledge BK-007 capitalized into business_domains/bon_buasson/business_knowledge.json.",
    "package_id": "KCAP-20260707T184043Z-b67ca6",
    "knowledge_id": "BK-007",
    "knowledge_type": "business",
    "domain": "bon_buasson"
  }
]
